myst/__init__.py
myst/client.py
myst/client_test.py
myst/constants.py
myst/constants_test.py
myst/exceptions.py
myst/exceptions_test.py
myst/google_id_token_auth.py
myst/google_id_token_auth_test.py
myst/resource.py
myst/resource_test.py
myst/user_credentials_cache.py
myst/user_credentials_cache_test.py
myst/data/__init__.py
myst/data/google_oauth_client_not_so_secret.json
myst/resources/__init__.py
myst/resources/time_series.py
myst/resources/time_series_test.py
myst/utils/__init__.py
myst/utils/auth_utils.py
myst/utils/auth_utils_test.py
myst/utils/cache_utils.py
myst/utils/cache_utils_test.py
myst/utils/core_utils.py
myst/utils/core_utils_test.py
myst/utils/requests_utils.py
myst/utils/requests_utils_test.py
myst/utils/retry_utils.py
myst/utils/retry_utils_test.py
myst/utils/validation_utils.py
myst/utils/validation_utils_test.py
myst-1.0.4.dist-info/LICENSE
myst-1.0.4.dist-info/METADATA
myst-1.0.4.dist-info/WHEEL
myst-1.0.4.dist-info/top_level.txt
myst-1.0.4.dist-info/RECORD
