Metadata-Version: 2.1
Name: myst
Version: 1.0.4
Summary: This is the official Python library for the Myst Platform.
Home-page: UNKNOWN
Author: Myst AI, Inc.
Author-email: support@myst.ai
License: Apache 2.0
Platform: UNKNOWN
Classifier: Development Status :: 3 - Alpha
Classifier: Programming Language :: Python
Classifier: Programming Language :: Python :: 2
Classifier: Programming Language :: Python :: 2.7
Classifier: Programming Language :: Python :: 3
Classifier: Programming Language :: Python :: 3.4
Classifier: Programming Language :: Python :: 3.5
Classifier: Programming Language :: Python :: 3.6
Classifier: Programming Language :: Python :: 3.7
Classifier: Programming Language :: Python :: Implementation :: PyPy
Requires-Python: >=2.7, !=3.0.*, !=3.1.*, !=3.2.*, !=3.3.*
Requires-Dist: google-auth (<2.0.0,>=1.11.0)
Requires-Dist: google-auth-oauthlib (<1.0.0,>=0.4.1)
Requires-Dist: pytz (>=2019.1)
Requires-Dist: requests (<3.0.0,>=2.21.0)
Requires-Dist: urllib3 (<2.0.0,>=1.24.3)
Requires-Dist: tenacity (<7.0.0,>=6.0.0)
Provides-Extra: dev
Requires-Dist: coverage (>=4.5.2) ; extra == 'dev'
Requires-Dist: mock (>=3.0.5) ; extra == 'dev'
Requires-Dist: responses (<1.0.0,>=0.10.6) ; extra == 'dev'
Requires-Dist: tox (<4.0.0,>=3.13.1) ; extra == 'dev'
Requires-Dist: readme-renderer (==24.0) ; extra == 'dev'
Requires-Dist: twine (>=1.13.0) ; extra == 'dev'
Requires-Dist: check-manifest (>=0.37) ; extra == 'dev'
